CHANGES.txt
CONTRIBUTORS.rst
MANIFEST.in
README.rst
base.cfg
bootstrap.py
buildout.cfg
checkouts.cfg
setup.py
sources.cfg
travis.cfg
versions.cfg
docs/LICENSE.GPL
docs/LICENSE.txt
docs/manual/fr/Makefile
docs/manual/fr/conf.py
docs/manual/fr/index.rst
src/collective/__init__.py
src/collective.local.workspace.egg-info/PKG-INFO
src/collective.local.workspace.egg-info/SOURCES.txt
src/collective.local.workspace.egg-info/dependency_links.txt
src/collective.local.workspace.egg-info/entry_points.txt
src/collective.local.workspace.egg-info/namespace_packages.txt
src/collective.local.workspace.egg-info/not-zip-safe
src/collective.local.workspace.egg-info/requires.txt
src/collective.local.workspace.egg-info/top_level.txt
src/collective/local/__init__.py
src/collective/local/workspace/__init__.py
src/collective/local/workspace/api.py
src/collective/local/workspace/configure.zcml
src/collective/local/workspace/content.py
src/collective/local/workspace/contentrules.py
src/collective/local/workspace/handlers.py
src/collective/local/workspace/interfaces.py
src/collective/local/workspace/permissions.zcml
src/collective/local/workspace/skins.zcml
src/collective/local/workspace/testing.py
src/collective/local/workspace/testing.zcml
src/collective/local/workspace/locales/collective.local.workspace.pot
src/collective/local/workspace/locales/plone.pot
src/collective/local/workspace/locales/rebuild_i18n.sh
src/collective/local/workspace/locales/fr/LC_MESSAGES/.gitignore
src/collective/local/workspace/locales/fr/LC_MESSAGES/collective.local.workspace.po
src/collective/local/workspace/locales/fr/LC_MESSAGES/plone.po
src/collective/local/workspace/profiles/default/metadata.xml
src/collective/local/workspace/profiles/default/propertiestool.xml
src/collective/local/workspace/profiles/default/rolemap.xml
src/collective/local/workspace/profiles/default/sharing.xml
src/collective/local/workspace/profiles/default/skins.xml
src/collective/local/workspace/profiles/default/types.xml
src/collective/local/workspace/profiles/default/workflows.xml
src/collective/local/workspace/profiles/default/types/workspace.xml
src/collective/local/workspace/profiles/default/workflows/workspace_workflow/definition.xml
src/collective/local/workspace/profiles/testing/metadata.xml
src/collective/local/workspace/skins/collective_local_workspace/workspace_icon.png
src/collective/local/workspace/tests/__init__.py
