Metadata-Version: 1.1
Name: collective.local.workspace
Version: 1.0rc2
Summary: A dexterity container that provides all collective.local features
Home-page: https://github.com/tdesvenain/collective.local.workspace
Author: Thomas Desvenain
Author-email: thomas.desvenain@gmail.com
License: gpl
Platform: UNKNOWN
Classifier: Environment :: Web Environment
Classifier: Framework :: Plone
Classifier: Framework :: Plone :: 4.2
Classifier: Framework :: Plone :: 4.3
Classifier: Operating System :: OS Independent
Classifier: Programming Language :: Python
Classifier: Programming Language :: Python :: 2
Classifier: Programming Language :: Python :: 2.6
Classifier: Programming Language :: Python :: 2.7
Classifier: Topic :: Software Development :: Libraries :: Python Modules
